diffword.py
diffword-0.1.0.dist-info/entry_points.txt
diffword-0.1.0.dist-info/WHEEL
diffword-0.1.0.dist-info/METADATA
diffword-0.1.0.dist-info/RECORD
