Metadata-Version: 2.1
Name: diffword
Version: 0.1.0
Summary: 
Author: ajanvrin
Author-email: alexandre.janvrin@reseau.eseo.fr
Requires-Python: >=3.9,<4.0
Classifier: Programming Language :: Python :: 3
Classifier: Programming Language :: Python :: 3.10
Classifier: Programming Language :: Python :: 3.9
Requires-Dist: click (>=8.0.3,<9.0.0)
Requires-Dist: python-docx-docm (>=0.1.0,<0.2.0)
Requires-Dist: regex (>=2022.1.18,<2023.0.0)
